[
 {
  "allow_on_submit": 0, 
  "bold": 0, 
  "collapsible": 0, 
  "collapsible_depends_on": null, 
  "columns": 0, 
  "default": null, 
  "depends_on": null, 
  "description": null, 
  "docstatus": 0, 
  "doctype": "Custom Field", 
  "dt": "Item", 
  "fieldname": "notifications", 
  "fieldtype": "Section Break", 
  "hidden": 0, 
  "ignore_user_permissions": 0, 
  "ignore_xss_filter": 0, 
  "in_global_search": 0, 
  "in_list_view": 0, 
  "in_standard_filter": 0, 
  "insert_after": "image", 
  "label": "Notifications", 
  "modified": "2018-06-13 05:49:54.798570", 
  "name": "Item-notifications", 
  "no_copy": 0, 
  "options": null, 
  "permlevel": 0, 
  "precision": "", 
  "print_hide": 0, 
  "print_hide_if_no_value": 0, 
  "print_width": null, 
  "read_only": 0, 
  "report_hide": 0, 
  "reqd": 0, 
  "search_index": 0, 
  "unique": 0, 
  "width": null
 }, 
 {
  "allow_on_submit": 0, 
  "bold": 0, 
  "collapsible": 0, 
  "collapsible_depends_on": null, 
  "columns": 0, 
  "default": "1", 
  "depends_on": null, 
  "description": null, 
  "docstatus": 0, 
  "doctype": "Custom Field", 
  "dt": "Item", 
  "fieldname": "notify_batch_expiration", 
  "fieldtype": "Check", 
  "hidden": 0, 
  "ignore_user_permissions": 0, 
  "ignore_xss_filter": 0, 
  "in_global_search": 0, 
  "in_list_view": 0, 
  "in_standard_filter": 0, 
  "insert_after": "notifications", 
  "label": "Notify Batch Expiration", 
  "modified": "2018-06-13 05:49:55.287368", 
  "name": "Item-notify_batch_expiration", 
  "no_copy": 0, 
  "options": null, 
  "permlevel": 0, 
  "precision": "", 
  "print_hide": 0, 
  "print_hide_if_no_value": 0, 
  "print_width": null, 
  "read_only": 0, 
  "report_hide": 0, 
  "reqd": 0, 
  "search_index": 0, 
  "unique": 0, 
  "width": null
 }, 
 {
  "allow_on_submit": 0, 
  "bold": 0, 
  "collapsible": 0, 
  "collapsible_depends_on": null, 
  "columns": 0, 
  "default": null, 
  "depends_on": "notify_batch_expiration", 
  "description": "Notify these many days before expiration", 
  "docstatus": 0, 
  "doctype": "Custom Field", 
  "dt": "Item", 
  "fieldname": "notify_expiration_before", 
  "fieldtype": "Data", 
  "hidden": 0, 
  "ignore_user_permissions": 0, 
  "ignore_xss_filter": 0, 
  "in_global_search": 0, 
  "in_list_view": 0, 
  "in_standard_filter": 0, 
  "insert_after": "notify_batch_expiration", 
  "label": "Notify Expiration Before", 
  "modified": "2018-06-13 05:57:15.932977", 
  "name": "Item-notify_expiration_before", 
  "no_copy": 0, 
  "options": null, 
  "permlevel": 0, 
  "precision": "", 
  "print_hide": 0, 
  "print_hide_if_no_value": 0, 
  "print_width": null, 
  "read_only": 0, 
  "report_hide": 0, 
  "reqd": 0, 
  "search_index": 0, 
  "unique": 0, 
  "width": null
 }, 
 {
  "allow_on_submit": 0, 
  "bold": 0, 
  "collapsible": 0, 
  "collapsible_depends_on": null, 
  "columns": 0, 
  "default": null, 
  "depends_on": null, 
  "description": null, 
  "docstatus": 0, 
  "doctype": "Custom Field", 
  "dt": "Batch", 
  "fieldname": "hide_expiry_notification", 
  "fieldtype": "Check", 
  "hidden": 0, 
  "ignore_user_permissions": 0, 
  "ignore_xss_filter": 0, 
  "in_global_search": 0, 
  "in_list_view": 0, 
  "in_standard_filter": 0, 
  "insert_after": "expiry_date", 
  "label": "Hide Expiry Notification", 
  "modified": "2018-06-13 08:16:11.651137", 
  "name": "Batch-hide_expiry_notification", 
  "no_copy": 0, 
  "options": null, 
  "permlevel": 0, 
  "precision": "", 
  "print_hide": 0, 
  "print_hide_if_no_value": 0, 
  "print_width": null, 
  "read_only": 0, 
  "report_hide": 0, 
  "reqd": 0, 
  "search_index": 0, 
  "unique": 0, 
  "width": null
 }
]